{
	"teacher": {
		"shaxsiy_malumotlar": {
			"ism": "Aziz",
			"familiya": "Karimov",
			"mutaxassislik": "Full-stack dasturchi",
			"email": "aziz.karimov@example.com",
			"telefon": "+998901234567",
			"manzil": "Toshkent shahar",
			"bio": "5 yillik tajribaga ega dasturlash o'qituvchisi",
			"profil_rasmi": "https://example.com/profiles/aziz.jpg",
			"status": "active"
		},
		"hisob_malumotlari": {
			"balans": 1750000,
			"pul_birligi": "so'm",
			"tolov_tizimlari": ["Payme", "Click", "Visa"],
			"oylik_xisobot": true
		},
		"kurslar": [
			{
				"kurs_id": "PY101",
				"nomi": "Python dasturlash asoslari",
				"darajasi": "Boshlang'ich",
				"tavsif": "Python dasturlash tilini noldan o'rganish kursi",
				"narx": {
					"bepul": true,
					"chegirma": 0,
					"asl_narx": 0
				},
				"reyting": {
					"umumiy": 4.8,
					"baholar_soni": 128
				},
				"statistika": {
					"user_soni": 542,
					"tamomlash_foizi": 78
				},
				"videolar": [
					{
						"video_id": "PY101-01",
						"sarlavha": "Python kirish",
						"url": "https://example.com/videos/python-intro",
						"vaqti": "15:23",
						"yuklangan_sana": "2023-01-10",
						"views": 1245,
						"faqat_onlayn": true,
						"streaming": {
							"format": "HLS",
							"max_sifat": "1080p",
							"tezlik_optimizatsiyasi": true
						},
						"DRM": {
							"turi": "Widevine",
							"holati": "active"
						}
					}
				],
				"modullar": [
					{
						"nomi": "Asosiy tushunchalar",
						"darslar_soni": 8,
						"tamomlangan": false
					}
				],
				"sertifikat": true
			}
		],
		"texnologiyalar": [
			{
				"nomi": "Python",
				"tajriba": "5 yil",
				"darajasi": "Kuchli"
			},
			{
				"nomi": "Django",
				"tajriba": "4 yil",
				"darajasi": "Kuchli"
			}
		],
		"loyihalar": [
			{
				"loyiha_id": "PR001",
				"nomi": "Online ta'lim platformasi",
				"tavsif": "Dasturlash kurslari uchun interaktiv platforma",
				"texnologiyalar": ["Django", "React", "PostgreSQL"],
				"link": "https://example.com/edu-platform",
				"ishchi_holatda": true,
				"github": "https://github.com/aziz/edu-platform"
			}
		],
		"ijtimoiy_tarmoqlar": {
			"github": "https://github.com/aziz",
			"linkedin": "https://linkedin.com/in/aziz",
			"telegram": "@azizcoder"
		},
		"sozlamalar": {
			"bildirishnomalar": true,
			"qorongilik_rejimi": false,
			"til": "uz"
		}
	},

	"user": {
		"shaxsiy_malumotlar": {
			"ism": "Dilshod",
			"familiya": "Rahimov",
			"email": "dilshod.rahimov@example.com",
			"telefon": "+998901112233",
			"manzil": "Samarqand",
			"bio": "Dasturlashni o'rganayotgan talaba",
			"profil_rasmi": "https://example.com/profiles/dilshod.jpg",
			"status": "active"
		},
		"hisob_malumotlari": {
			"balans": 750000,
			"pul_birligi": "so'm",
			"bonuslar": 25000
		},
		"sotib_olingan_kurslar": [
			{
				"kurs_id": "PY101",
				"nomi": "Python dasturlash asoslari",
				"o'qituvchi": "Aziz Karimov",
				"sotib_olish_sana": "2023-06-10",
				"turi": "doimiy",
				"narxi": 499000,
				"progress": 65,
				"oxirgi_kirish": "2023-08-20T14:30:00"
			}
		],
		"platforma_sozlamalari": {
			"video_qualiteti": {
				"avtomatik": true,
				"standart": "720p"
			},
			"internet_talablari": {
				"min_tezlik": "2 Mbps",
				"tavsiya_etilgan": "5 Mbps"
			}
		},
		"texnik_qo'llab-quvvat": {
			"aloqa": "support@platforma.uz"
		}
	}
}
